mhubio/__init__.py
mhubio/keys.py
mhubio/run.py
mhubio/core/Config.py
mhubio/core/DataHandler.py
mhubio/core/DataHandler2.py
mhubio/core/DataType.py
mhubio/core/DataTypeQuery.py
mhubio/core/DirectoryChain.py
mhubio/core/Error.py
mhubio/core/FileType.py
mhubio/core/IO.py
mhubio/core/IO_wip.py
mhubio/core/Instance.py
mhubio/core/InstanceData.py
mhubio/core/InstanceDataBundle.py
mhubio/core/InstanceDataCollection.py
mhubio/core/Logger.py
mhubio/core/Meta.py
mhubio/core/Module.py
mhubio/core/OutputDataCollection.py
mhubio/core/RunnerOutput.py
mhubio/core/__init__.py
mhubio/core/templates.py
mhubio/experiments/configtest.py
mhubio/experiments/dicomseg.py
mhubio/experiments/empty_dict_issue.py
mhubio/experiments/metatest.py
mhubio/experiments/organizer.py
mhubio/experiments/run.min.py
mhubio/experiments/run.py
mhubio/experiments/test.py
mhubio/modules/__init__.py
mhubio/modules/convert/DataConverter.py
mhubio/modules/convert/DicomConverter.py
mhubio/modules/convert/DsegConverter.py
mhubio/modules/convert/MhaConverter.py
mhubio/modules/convert/MhaConverterPanimg.py
mhubio/modules/convert/NiftiConverter.py
mhubio/modules/convert/NiftiConverter__old.py
mhubio/modules/convert/NrrdConverter.py
mhubio/modules/convert/RTStructConverter.py
mhubio/modules/convert/RTStructConverter_DSEG.py
mhubio/modules/convert/TiffConverter.py
mhubio/modules/convert/__init__.py
mhubio/modules/exporter/ImageExporter.py
mhubio/modules/exporter/JsonSegExporter.py
mhubio/modules/exporter/ReportExporter.py
mhubio/modules/exporter/__init__.py
mhubio/modules/filter/AttributeFilter.py
mhubio/modules/filter/FileFilter.py
mhubio/modules/filter/InstanceFilter.py
mhubio/modules/filter/__init__.py
mhubio/modules/importer/DataImporter.py
mhubio/modules/importer/DataSorter.py
mhubio/modules/importer/DicomImporter.py
mhubio/modules/importer/FileStructureImporter.py
mhubio/modules/importer/FilieListImporter.py
mhubio/modules/importer/NrrdImporter.py
mhubio/modules/importer/UnsortedDicomImporter.py
mhubio-0.0.2.dist-info/METADATA
mhubio-0.0.2.dist-info/WHEEL
mhubio-0.0.2.dist-info/top_level.txt
mhubio-0.0.2.dist-info/RECORD
