Metadata-Version: 2.1
Name: mhubio
Version: 0.0.2
Summary: The glue layer framework used to harmonize MHub model's input and output data.
Home-page: https://github.com/MHubAI/mhubio
Author: Leonard Nürnberg
Author-email: lnuernberg@bwh.harvard.edu
License: MIT
Keywords: mhub
Classifier: Development Status :: 4 - Beta
Classifier: Topic :: Software Development :: Libraries :: Python Modules
Classifier: License :: OSI Approved :: MIT License
Requires-Dist: pyyaml
Requires-Dist: typing-extensions ==4.5.0
